weather/__init__.py
weather/ob_havo.py
Obhavo-0.4.dist-info/LICENCE
Obhavo-0.4.dist-info/METADATA
Obhavo-0.4.dist-info/WHEEL
Obhavo-0.4.dist-info/top_level.txt
Obhavo-0.4.dist-info/RECORD
