Metadata-Version: 2.1
Name: Obhavo
Version: 0.4
Summary: ObhavoUz
Home-page: https://github.com/begyy/obhavo
Author: Sadullayev Bekhzod
Author-email: begymrx@gmail.com
License: UNKNOWN
Platform: UNKNOWN
Classifier: Programming Language :: Python :: 3
Classifier: License :: OSI Approved :: MIT License
Classifier: Operating System :: OS Independent
